{
  "unit_id": "multiple-text",
  "unit_name_jp": "複数文章統合読解",
  "grade": "英語（共通テスト第4問・第6問B相当）",
  "patterns": [
    {
      "pattern_id": "basic-individual-info",
      "description": "2つの文書（ブログ＋コメント、記事＋告知など）から、それぞれの文書に書かれている個別情報を取り出す",
      "thinking_process": [
        "どちらの文書を読めばよいかを設問から判断する",
        "該当する文書を丁寧に読み、設問で問われている情報を探す",
        "選択肢と本文の記述を照合し、正しく一致するものを選ぶ"
      ],
      "common_mistakes": [
        "2つの文書の情報を混同してしまう",
        "似た単語・数字で別の内容の選択肢を選んでしまう"
      ],
      "difficulty": "basic"
    },
    {
      "pattern_id": "basic-purpose-and-topic",
      "description": "2つの文書の目的・話題を把握し、各文書が「何について述べているか」を特定する",
      "thinking_process": [
        "各文書の冒頭・タイトル・キーワードを確認して話題を把握する",
        "設問が「どちらの文書に書かれているか」を問う場合、各文書を確認する",
        "話題・目的が選択肢と一致するかを本文に戻って確認する"
      ],
      "common_mistakes": [
        "本文を読まずにタイトルだけで判断してしまう",
        "文書の話題ではなく自分の知識で答えてしまう"
      ],
      "difficulty": "basic"
    },
    {
      "pattern_id": "basic-factual-retrieval",
      "description": "2つの文書のうち一方に書かれている事実（人名・日付・場所・数値など）を正確に取り出す",
      "thinking_process": [
        "設問のキーワードを確認し、どちらの文書に該当情報があるかを見当をつける",
        "該当文書をスキャンして数値・固有名詞などを探す",
        "選択肢と本文の記述を一字一句比較して正解を決める"
      ],
      "common_mistakes": [
        "数字や固有名詞を別の文書のものと混同する",
        "選択肢に似た数値が含まれている場合に焦って選んでしまう"
      ],
      "difficulty": "basic"
    },
    {
      "pattern_id": "standard-compare-views",
      "description": "2つの文書の筆者・話者の主張や意見を比較し、一致点・相違点を正しく把握する",
      "thinking_process": [
        "各文書で筆者が「何を主張しているか」を段落ごとにまとめる",
        "2つの主張を比べ、共通している部分と違う部分を整理する",
        "選択肢が「両者が同意している点」か「一方だけが述べている点」かを判断する"
      ],
      "common_mistakes": [
        "どちらの文書のどちらの意見かを混同する",
        "一方の文書にしか書かれていないことを「両者の共通意見」と誤解する"
      ],
      "difficulty": "standard"
    },
    {
      "pattern_id": "standard-integrate-info",
      "description": "2つの文書に散らばった情報を統合して、設問に答える（例：記事＋返信メールの内容を合わせて解釈する）",
      "thinking_process": [
        "設問が求める情報が、どちらの文書のどの部分に関係するかを特定する",
        "2つの文書の情報を組み合わせて論理的な結論を導く",
        "選択肢が組み合わせた情報と矛盾しないかを確認する"
      ],
      "common_mistakes": [
        "一方の文書の情報だけで判断し、もう一方を見落とす",
        "各文書の情報を正しく組み合わせずに誤った結論を出す"
      ],
      "difficulty": "standard"
    },
    {
      "pattern_id": "standard-fact-vs-opinion",
      "description": "2つの文書において「事実として述べられていること」と「意見・推測として述べられていること」を区別する",
      "thinking_process": [
        "各文書で断定的な表現（facts）と推測・意見の表現（I think / may / should 等）を区別する",
        "設問が「両者が事実として認めていること」を問う場合、推測・意見を含む選択肢を除外する",
        "残った選択肢を本文と照合して正解を選ぶ"
      ],
      "common_mistakes": [
        "I think / seem / appear 等を「事実」として扱ってしまう",
        "一方の文書の事実を他方にも当てはめてしまう"
      ],
      "difficulty": "standard"
    },
    {
      "pattern_id": "exam-only-one-document",
      "description": "「どちらか一方の文書にのみ述べられていること」を選ぶ（NOT問題・片方のみ問題）",
      "thinking_process": [
        "選択肢を一つずつ確認し、両方の文書で言及されているか片方だけかを判定する",
        "「両方に書いてある」選択肢を消去し、「片方だけ」のものを特定する",
        "設問が「文書Xにのみ述べられていること」を問う場合、文書Yを必ず確認して除外する"
      ],
      "common_mistakes": [
        "両方の文書を確認しないで片方だけで判断する",
        "「似た内容」を「同じ内容」と誤解し、どちらにも書いてあると思ってしまう"
      ],
      "difficulty": "exam"
    },
    {
      "pattern_id": "exam-both-documents-agree",
      "description": "「両方の文書に共通して述べられていること」を選ぶ（共通情報の抽出）",
      "thinking_process": [
        "選択肢を一つずつ確認し、2つの文書の両方に同じ内容が書かれているかを確かめる",
        "片方にしかない情報を含む選択肢は除外する",
        "同じ「考え」や「事実」が文書をまたいで共通しているものを選ぶ"
      ],
      "common_mistakes": [
        "一方の文書に書いてある情報を「両者共通」と誤解する",
        "同じ内容が異なる表現で書かれているときに別のことだと思ってしまう"
      ],
      "difficulty": "exam"
    },
    {
      "pattern_id": "exam-writer-intent-comparison",
      "description": "2つの文書の筆者がそれぞれ「最も伝えたいこと（主題・メッセージ）」を特定し、比較する",
      "thinking_process": [
        "各文書の冒頭・結び・繰り返し使われる表現から「主題」を把握する",
        "設問が「筆者Aと筆者Bが共通して伝えたいこと」を問う場合、主張の核を比較する",
        "選択肢のうち、両方の文書の主題と一致するものを選ぶ"
      ],
      "common_mistakes": [
        "文書の細部（具体例）をメインメッセージと間違える",
        "2つの筆者の意図が異なる場合に「どちらかのみが述べていること」を「共通メッセージ」と誤解する"
      ],
      "difficulty": "exam"
    }
  ]
}
