{
  "as-001": {
    "lead": "等差数列の一般項は「初項 + (n−1) × 公差」。n番目という意味で n−1 個分の公差を足すことを忘れずに。",
    "steps": [
      "一般項の公式：aₙ = a + (n−1)d に初項 a=3、公差 d=4 を代入する。",
      "aₙ = 3 + (n−1) × 4 = 3 + 4n − 4 = 4n − 1。",
      "確認：n=1 → a₁ = 3、n=2 → a₂ = 7（公差 4 で正しい）。"
    ],
    "common_mistakes": [
      "「a + n×d」としてしまうと n=1 のとき a+d になり初項がずれる。(n−1) をかけるのが正しい。",
      "初項と公差を逆にして「4 + (n−1)×3」としないよう注意。初項が a₁=3 であることを確認する。"
    ],
    "tips": [
      "一般項の公式は aₙ = a + (n−1)d。これを変形すると aₙ = dn + (a−d) の一次式になる。",
      "n=1 で確認するクセをつけると間違いが防げる。"
    ]
  },
  "as-002": {
    "lead": "2つの項の値から「差」をとると公差を求められる。そのあと初項を逆算する。",
    "steps": [
      "a₇ − a₃ = {a+6d} − {a+2d} = 4d = 27 − 11 = 16 → d = 4。",
      "a₃ = a + 2d = 11 → a = 11 − 8 = 3。",
      "確認：a₁=3, d=4。a₃=3+8=11✓、a₇=3+24=27✓。"
    ],
    "common_mistakes": [
      "「a₃ = a + 3d」とする誤り（第3項は初項から3回公差を足すのではなく2回）。一般項は a + (n−1)d。",
      "公差を「(a₇−a₃)/(7−3) = 4」で求めるのは正しいが、分母は項番号の差（位置の差）。"
    ],
    "tips": [
      "第m項と第n項の差から公差：d = (aₙ − aₘ)/(n − m)。",
      "公差が分かったらどれか1項の値から初項を逆算する。"
    ]
  },
  "as-003": {
    "lead": "等差中項の条件：3数 a, b, c が等差数列 ⟺ b−a = c−b ⟺ 2b = a+c（b は両端の平均）。",
    "steps": [
      "3数 3, x, 11 が等差数列 → 等差中項の条件 2x = 3 + 11 = 14 → x = 7。",
      "確認：公差 d = 7−3 = 4 = 11−7 = 4 ✓。"
    ],
    "common_mistakes": [
      "等比中項と混同して「x² = 3×11」としてしまう誤り。等差は足し算、等比は掛け算の条件が違う。",
      "3数の和を3で割って平均を求める方法でも答えは同じ（x は中央の値なので平均に等しい）。"
    ],
    "tips": [
      "等差中項：2b = a+c（b は a と c の算術平均）。",
      "等比中項：b² = ac（b は a と c の幾何平均）。混乱しやすいので定義を確認。"
    ]
  },
  "as-004": {
    "lead": "等差数列の和の公式 Sₙ = n{2a+(n−1)d}/2 は必須。末項が分かる場合は Sₙ = n(a+l)/2 も使える。",
    "steps": [
      "初項 a=2、公差 d=3、項数 n=20。",
      "S₂₀ = 20×{2×2+(20−1)×3}/2 = 20×{4+57}/2 = 20×61/2 = 610。",
      "別解：末項 a₂₀ = 2+19×3 = 59。S₂₀ = 20×(2+59)/2 = 20×61/2 = 610✓。"
    ],
    "common_mistakes": [
      "「n{2a+(n−1)d}」で 2 で割るのを忘れる → 1220 という誤り。公式の分母 2 を必ず書く。",
      "末項を a₂₀ = a+20d = 2+60 = 62 と計算する誤り。末項は a+(n−1)d なので n=20 なら 19 倍。"
    ],
    "tips": [
      "Sₙ = n/2 × (初項+末項)。これを使うには末項を先に求める必要がある。",
      "n が大きいときは先に末項を求めてから n(a+l)/2 で計算するとシンプル。"
    ]
  },
  "as-005": {
    "lead": "Sₙ から aₙ を求めるには「aₙ = Sₙ − Sₙ₋₁ (n≥2)」、そして n=1 のとき別途 a₁=S₁ を確認する。",
    "steps": [
      "n ≥ 2：aₙ = Sₙ − Sₙ₋₁ = (n²+3n) − {(n−1)²+3(n−1)}。",
      "展開：= n²+3n − (n²−2n+1+3n−3) = n²+3n − n²+2n−1−3n+3 = 2n+2。",
      "n=1：a₁ = S₁ = 1+3 = 4。公式に代入：2×1+2 = 4 ✓ → aₙ = 2n+2（すべての n で成立）。"
    ],
    "common_mistakes": [
      "Sₙ を n で割って aₙ を求めようとする誤り（Sₙ/n は平均であり aₙ ではない）。",
      "n=1 の確認を省略する誤り。Sₙ が2次式の場合、n≥2 の公式が n=1 に成立しないことがある。"
    ],
    "tips": [
      "aₙ = Sₙ − Sₙ₋₁ は n≥2 のときのみ使える。必ず n=1 を別に確認する。",
      "Sₙ が n の2次式（最高次係数 p）なら公差 d = 2p。"
    ]
  },
  "as-006": {
    "lead": "「第何項か」はaₙ = 値 という方程式を解く問題。一般項の公式に代入して n を求める。",
    "steps": [
      "aₙ = 5 + (n−1)×3 = 77 と設定する。",
      "3(n−1) = 72 → n−1 = 24 → n = 25。",
      "確認：a₂₅ = 5+24×3 = 5+72 = 77 ✓。"
    ],
    "common_mistakes": [
      "n = (77−5)/3 = 24 として第 24 項とする誤り。これは (n−1) の値なので n = 25 が正しい。",
      "77 が等差数列の項であるかを確認しないまま n を求める（77−5=72 が公差 3 の倍数であることを確認）。"
    ],
    "tips": [
      "第何項かを求める手順：aₙ = 目標値 → n を解く → n が正の整数であることを確認。",
      "n = (目標値 − 初項)/公差 + 1 と覚えると速い。"
    ]
  },
  "as-007": {
    "lead": "奇数の列は初項1、公差2の等差数列。1〜99（または1〜100の奇数）の和は等差数列の和公式で求める。",
    "steps": [
      "1以上100以下の奇数：1, 3, 5, ..., 99。初項 1、末項 99、公差 2。",
      "項数：(99−1)/2 + 1 = 50 個。",
      "和 = 50×(1+99)/2 = 50×50 = 2500。"
    ],
    "common_mistakes": [
      "項数を 100/2 = 50 と求めるのは正しいが「100以下の奇数は50個」という事実を使う。",
      "1+3+5+...+(2n−1) = n² という公式を使っても。n=50 → 50²=2500。"
    ],
    "tips": [
      "1から (2n−1) までの奇数の和 = n²（重要公式）。1〜99は n=50 なので 50²=2500。",
      "項数は (末項−初項)/公差 + 1 で求める。"
    ]
  },
  "as-008": {
    "lead": "数列が等差数列かを確認するには「隣接する差が一定」であることをチェックする。その後一般項を公式で立てる。",
    "steps": [
      "差を確認：7−4=3, 10−7=3, 13−10=3。一定 → 等差数列。",
      "初項 a₁=4、公差 d=3 の等差数列。",
      "aₙ = 4+(n−1)×3 = 3n+1。確認：n=1 → 4✓, n=2 → 7✓。"
    ],
    "common_mistakes": [
      "「4n−3+4 = 4n+1」という式は公差を 4 と誤解した結果。公差は隣接差 = 3。",
      "「3n+4」は n=1 のとき 7 になり初項 4 と一致しない。n=1 の確認が必須。"
    ],
    "tips": [
      "一般項 aₙ = dn + (a₁−d)。例：a₁=4, d=3 → 3n+(4−3) = 3n+1。",
      "n=1 を代入して a₁ と一致するかを必ず確認する。"
    ]
  },
  "as-009": {
    "lead": "2つの等差数列の共通項も等差数列をなす。共通項の公差は2つの数列の公差の最小公倍数。",
    "steps": [
      "数列A（初項3, 公差4）：3, 7, 11, 15, 19, 23, 27, ...。",
      "数列B（初項4, 公差3）：4, 7, 10, 13, 16, 19, 22, 25, ...。",
      "共通項を直接確認：7（A の第2項、B の第2項）が最初の共通項。",
      "共通項の公差：LCM(4,3)=12。共通数列：7, 19, 31, ...。"
    ],
    "common_mistakes": [
      "「公差が同じでないと共通項はない」という誤解。公差が異なっても共通項は存在しうる。",
      "共通項を求めずに「LCM=12 が公差」だけ使う場合は初項を別途求める必要がある。"
    ],
    "tips": [
      "共通項の公差 = LCM(d₁, d₂)。初項は直接探索か連立方程式で求める。",
      "小さい値で直接書き出して確認するのが確実で速い。"
    ]
  },
  "as-010": {
    "lead": "3数を「a−d, a, a+d」と置くと和が 3a になり計算が楽。この対称な置き方を活用する。",
    "steps": [
      "和：(a−d)+a+(a+d) = 3a = 15 → a = 5。",
      "積：(a−d)×a×(a+d) = a(a²−d²) = 5(25−d²) = 105 → 25−d² = 21 → d² = 4 → d = ±2。",
      "3数：d=2 のとき 3, 5, 7。d=−2 のとき 7, 5, 3（同じ数列の逆順）。"
    ],
    "common_mistakes": [
      "3数を「a, a+d, a+2d」と置くと和が 3a+3d となり計算が面倒。a−d, a, a+d を使う方が対称で速い。",
      "積の公式 a(a²−d²) は (a−d)×a×(a+d) = a{(a−d)(a+d)} = a(a²−d²) の展開。符号に注意。"
    ],
    "tips": [
      "等差3数の対称な置き方：a−d, a, a+d。和→3a が楽、積→a(a²−d²) が楽。",
      "4数の場合は a−3d, a−d, a+d, a+3d（公差が 2d の等差数列）。"
    ]
  },
  "as-011": {
    "lead": "初項正・公差負の等差数列では、項が正の間は和が増え、負になると和が減る。aₙ≥0の最後の項までの和が最大。",
    "steps": [
      "aₙ = 20+(n−1)×(−3) = 23−3n ≥ 0 → n ≤ 23/3 ≈ 7.67 → n ≤ 7。",
      "a₇ = 23−21 = 2 > 0 ✓、a₈ = 23−24 = −1 < 0。",
      "S₇ = 7×(20+2)/2 = 7×11 = 77。"
    ],
    "common_mistakes": [
      "公差が負だから「和は単調減少」という誤解。初項が正の場合は最初のうちは和が増加する。",
      "aₙ = 0 となる n が整数でない場合は、その前後の整数で S を比較して大きい方が最大。"
    ],
    "tips": [
      "最大となる n の求め方：aₙ ≥ 0 の最大の n = k。Sₙ の最大は Sₖ または Sₖ₊₁（a = 0 の場合は両方同じ）。",
      "式だけで判断：S₇ と S₈ を比較すれば確認できる（S₈ = S₇ + a₈ = 77+(−1) = 76 < 77）。"
    ]
  },
  "as-012": {
    "lead": "「n以下のkの倍数の和」は等差数列の和公式で求める。初項=k、末項=k×⌊n/k⌋、項数=⌊n/k⌋。",
    "steps": [
      "1以上100以下の3の倍数：3, 6, 9, ..., 99。",
      "項数 = 99/3 = 33 個。初項 3、末項 99。",
      "和 = 33×(3+99)/2 = 33×51 = 1683。"
    ],
    "common_mistakes": [
      "「1+2+...+100 = 5050 を3で割る」は誤り。5050 は全整数の和であり、3の倍数のみの和ではない。",
      "項数を 100/3 ≈ 33.3 → 33 と求めるのは正しいが、末項は 99（100 ではない）。"
    ],
    "tips": [
      "n以下の k の倍数の個数：⌊n/k⌋（床関数（⌊⌋））。",
      "和 = k × (1+2+...+⌊n/k⌋) = k × ⌊n/k⌋×(⌊n/k⌋+1)/2 と整理できる。"
    ]
  },
  "as-013": {
    "lead": "初項が負・公差が正の場合は和が最初に最小値をとり、項が正になるにつれて増加する。",
    "steps": [
      "aₙ = −2+5(n−1) = 5n−7 ≤ 0 → n ≤ 7/5 = 1.4 → n ≤ 1。",
      "a₁ = −2 < 0、a₂ = 3 > 0。負の項は a₁ のみ。",
      "S₁ = −2 < S₂ = −2+3 = 1。よって S₁ = −2 が最小。"
    ],
    "common_mistakes": [
      "「公差が正だから和は単調増加」という誤解。初項が負の場合は最初は和が減ることもある。",
      "S₀ = 0 と比較して S₁ = −2 < 0 なので n=1 が最小。n=0 は「0項の和」で通常考えない。"
    ],
    "tips": [
      "和の最小は「負の項が尽きるまでの和」が最小。aₙ ≤ 0 の最後の n で最小値をとる。",
      "aₙ の符号変化の前後（n=k と n=k+1）の S を比較して確定させる。"
    ]
  },
  "as-014": {
    "lead": "公差は「2項の値の差 ÷ 位置の差」で求まる。初項を求めたら不等式を立てて n を特定する。",
    "steps": [
      "公差 d = (a₁₂ − a₅)/(12 − 5) = (38−11)/7 = 21/7 = 3。",
      "初項 a = a₅ − 4d = 17 − 12 = 5。",
      "aₙ = 5+3(n−1) = 3n+2 > 100 → 3n > 98 → n > 32.67 → n = 33。",
      "確認：a₃₃ = 3×33+2 = 101 > 100、a₃₂ = 3×32+2 = 98 ≤ 100 ✓。"
    ],
    "common_mistakes": [
      "「n = (100−5)/3 + 1 = 32.67 → n = 32」と誤解する。不等式は「>」なので切り上げて n = 33。",
      "aₙ = 100 を「=」で解いた n は境界値で「超える」のは次の整数。"
    ],
    "tips": [
      "「初めて〜を超える n」は aₙ > M の不等式を解いて切り上げ（天井関数）。",
      "「初めて〜以上になる n」は aₙ ≥ M の不等式を解いて切り上げ。"
    ]
  },
  "as-015": {
    "lead": "Sₙ の展開から一般項を求め、初項と公差を特定する。Sₙ = dn²/2 + (a−d/2)n の係数比較も有効。",
    "steps": [
      "a₁ = S₁ = 2×1²−1 = 1。",
      "n ≥ 2：aₙ = Sₙ−Sₙ₋₁ = (2n²−n) − {2(n−1)²−(n−1)} = 2n²−n−2n²+4n−2+n−1 = 4n−3。",
      "n=1 確認：4×1−3 = 1 = a₁ ✓ → aₙ = 4n−3（初項 1、公差 4）。"
    ],
    "common_mistakes": [
      "微分して「dSₙ/dn = 4n−1 → 初項 3」とするのは誤り（微積分は n が連続変数のときの手法）。",
      "Sₙ を n で割っても aₙ は出ない。「Sₙ/n = 2n−1」は各項の平均であり一般項ではない。"
    ],
    "tips": [
      "Sₙ = pn²+qn のとき：公差 d = 2p、初項 a = p+q（これを覚えておくと速い）。",
      "この問題では p=2, q=−1 → d=4, a=2+(−1)=1。"
    ]
  },
  "as-016": {
    "lead": "「A でも B でも割り切れる」は「A と B の最小公倍数の倍数」と同じ意味。",
    "steps": [
      "4 と 6 の最小公倍数（LCM）= 12。",
      "1以上200以下の 12 の倍数：12, 24, ..., 192（12×16=192 ≤ 200 < 12×17=204）。",
      "項数 = 16 個。和 = 16×(12+192)/2 = 16×102 = 1632。"
    ],
    "common_mistakes": [
      "「4の倍数の和 + 6の倍数の和」は和集合の和であり、共通項（12の倍数）が二重に加算される誤り。",
      "「4でも6でも」は AND 条件（積集合）。LCM を使う。"
    ],
    "tips": [
      "「AまたはBの倍数」→ A の倍数の和 + B の倍数の和 − LCM(A,B) の倍数の和（包除原理）。",
      "「AかつBの倍数」→ LCM(A,B) の倍数の和。"
    ]
  },
  "as-017": {
    "lead": "S₁₀ と S₂₀ の2つの条件から連立方程式を作り、公差と初項を求める。",
    "steps": [
      "S₁₀ = 5(2a+9d) = 100 → 2a+9d = 20 … ①。",
      "S₂₀ = 10(2a+19d) = 300 → 2a+19d = 30 … ②。",
      "② − ① : 10d = 10 → d = 1。",
      "① に代入：2a+9 = 20 → a = 11/2 = 5.5。"
    ],
    "common_mistakes": [
      "S₂₀/S₁₀ = 3 から「等比数列」と誤解するケース。等差数列でも Sₙ の比が整数になることはある。",
      "S₂₀ = 10(2a+19d) の係数（先頭の 10）を忘れ 20(2a+19d) とする誤り。"
    ],
    "tips": [
      "Sₙ = n{2a+(n−1)d}/2。n を決めて代入すると a と d の一次方程式が立つ。2式立てて連立する。",
      "引き算で公差を先に求め、それから初項を逆算する流れが標準的。"
    ]
  },
  "as-018": {
    "lead": "一般項 aₙ = −2n+21 から aₙ ≥ 0 の最大 n を求め、その n での Sₙ が最大値。",
    "steps": [
      "aₙ = −2n+21 ≥ 0 → n ≤ 10.5 → n ≤ 10。",
      "a₁₀ = −20+21 = 1 > 0、a₁₁ = −22+21 = −1 < 0。",
      "初項 a₁ = 19、末項（n=10）a₁₀ = 1。S₁₀ = 10×(19+1)/2 = 100。"
    ],
    "common_mistakes": [
      "n = 10.5 だから「n=10 か n=11 を比較」と考えるのは正しいが S₁₁ = S₁₀ + a₁₁ = 100+(−1) = 99 < 100 なので S₁₀ が最大。",
      "公差を確認：aₙ = −2n+21 の係数から d = −2。d < 0 なのでいつか最大値をとる。"
    ],
    "tips": [
      "最大の Sₙ：aₙ の符号が正から負に変わる n=k の近辺を確認。Sₖ と Sₖ₊₁ を比較。",
      "S₁₀ = 10×(a₁+a₁₀)/2 = 10×(19+1)/2 = 100 は末項利用の公式でシンプル。"
    ]
  },
  "as-019": {
    "lead": "Sₙ = n² という条件から aₙ を求めると、aₙ = 2n−1（奇数列）であることが分かる。",
    "steps": [
      "n ≥ 2：aₙ = Sₙ−Sₙ₋₁ = n²−(n−1)² = n²−n²+2n−1 = 2n−1。",
      "n=1：a₁ = S₁ = 1。公式に代入：2×1−1 = 1 ✓。",
      "初項 a₁=1、公差 d=2（連続奇数）。Sₙ=n² は1+3+5+...+(2n−1)=n² の有名公式。"
    ],
    "common_mistakes": [
      "√Sₙ = n → aₙ = n とする誤り。aₙ ≠ √Sₙ。Sₙ は和であり aₙ とは別物。",
      "係数比較でも求められる：Sₙ = n{2a+(n−1)d}/2 = dn²/2+(a−d/2)n = n²。d/2=1 → d=2、a−d/2=0 → a=1。"
    ],
    "tips": [
      "1+3+5+...+(2n−1) = n²（1からnまでの奇数の和）は頻出公式。",
      "Sₙ = pn² の形 → 公差 d = 2p、初項 a = p（定数項なし）。"
    ]
  },
  "as-020": {
    "lead": "等差×等比の混合 Σk×2^k は「ずらし差分法（S−rS の計算）」で解く。シグマの分離積は使えない。",
    "steps": [
      "S = 1×2 + 2×2² + 3×2³ + ... + n×2ⁿ とおく。",
      "2S = 1×2² + 2×2³ + ... + (n−1)×2ⁿ + n×2ⁿ⁺¹。",
      "S − 2S = S(1−2) = −S = 1×2 + 2² + 2³ + ... + 2ⁿ − n×2ⁿ⁺¹。",
      "−S = 2(2ⁿ−1)/(2−1) − n×2ⁿ⁺¹ = 2ⁿ⁺¹−2 − n×2ⁿ⁺¹。",
      "S = n×2ⁿ⁺¹ − 2ⁿ⁺¹ + 2 = (n−1)×2ⁿ⁺¹ + 2。"
    ],
    "common_mistakes": [
      "Σk×2^k = (Σk)×(Σ2^k) とシグマを分離するのは誤り。積の和は和の積ではない。",
      "2S を計算するとき各項の係数のずれに注意。S の第 k 項は k×2^k、2S の第 k 項は k×2^(k+1)。"
    ],
    "tips": [
      "等差×等比型 Σk×rⁿ の和 → S − rS の「ずらし差分法」一択。",
      "ずらした後は等比数列の和 Σrⁿ を使って整理する。"
    ]
  },
  "as-021": {
    "lead": "S₁₅ = S₂₀ は a と d の関係を一つ与える。連立してから問題を解く。",
    "steps": [
      "S₁₅ = S₂₀ → S₂₀ − S₁₅ = a₁₆+a₁₇+a₁₈+a₁₉+a₂₀ = 0。",
      "5項の等差数列の和 = 0 → 中央の第18項 a₁₈ = 0。",
      "a₁₅ = S₁₅ の公式：15(2a+14d)/2 = 15(2a+14d)/2。別法：連立方程式。",
      "S₁₅=15(2a+14d)/2=15(a+7d)=S₂₀=20(a+19d)/2=10(a+19d/2)... 15a+105d=10a+95d+... 計算して a=−17d。初項 a > 0, d < 0 の確認 ✓。"
    ],
    "common_mistakes": [
      "「S₁₅=S₂₀ → S は n=15〜20 で定数」という誤解。Sₙ は最大値付近で S₁₅=S₂₀ のとき中間に極大がある。",
      "a = −17d という関係が導かれたとき、初項正・公差負の条件 a > 0, d < 0 を確認する。"
    ],
    "tips": [
      "Sₘ = Sₙ のとき a(m+1) 〜 aₙ の和が 0 → 中央項 = 0 という性質を使うと速い。",
      "S の最大値は aₙ が0になる近辺（第 17 か 18 項付近）にある。"
    ]
  },
  "as-022": {
    "lead": "公差が正で初項が負の等差数列では、負の項がなくなるタイミングで Sₙ が最小になる。",
    "steps": [
      "d > 0, a < 0 の設定。aₙ = a+(n−1)d ≤ 0 となる最大の n を m とする。",
      "aₘ ≤ 0 < aₘ₊₁ → Sₘ か Sₘ₊₁ が最小。",
      "Sₘ₊₁ = Sₘ + aₘ₊₁ > Sₘ（aₘ₊₁ > 0 なので）",
      "よって Sₘ が最小（ただし aₘ = 0 のとき Sₘ = Sₘ₋₁）。"
    ],
    "common_mistakes": [
      "「公差 > 0 なら和は単調増加」は初項が正のときの話。初項が負なら最初は和が減る。",
      "最小は Sₘ か Sₘ₋₁ か迷う場合は aₘ の符号で判断：aₘ < 0 なら Sₘ の方が Sₘ₋₁ より小さい。"
    ],
    "tips": [
      "最小/最大の判定は常に「aₙ の符号変化」を追う。",
      "aₙ ≤ 0 の最大 n を m として Sₘ が最小。"
    ]
  },
  "as-023": {
    "lead": "奇数項と偶数項の和の差から、各対応する項の差（= 公差）が求まる。",
    "steps": [
      "奇数項の和：a₁+a₃+...+a₂ₙ₋₁ = n²。",
      "偶数項の和：a₂+a₄+...+a₂ₙ = n²+n。",
      "差：(a₂−a₁)+(a₄−a₃)+...+(a₂ₙ−a₂ₙ₋₁) = n²+n−n² = n。",
      "各差は公差 d なので n × d = n → d = 1。"
    ],
    "common_mistakes": [
      "奇数項と偶数項の和を「別の等差数列の和」として扱うのも正しいが計算が複雑になる。",
      "和の差 = n が「n 個の公差の合計 nd」に等しい点に気づくことが鍵。"
    ],
    "tips": [
      "a₂ₖ − a₂ₖ₋₁ = d（隣接差は常に公差）。これが n 個あるので合計 = nd。",
      "条件式が2つあるので初項も求められる：a₁+a₃+...の第1項 a₁ = S₁(奇数) − (合計の一部)で逆算。"
    ]
  },
  "as-024": {
    "lead": "不等式から公差の範囲を求め、整数条件と初項の条件を組み合わせて絞り込む。",
    "steps": [
      "a₅ = a+4d = 10 → a = 10−4d。",
      "a₃₂ > 100：(10−4d)+31d = 10+27d > 100 → 27d > 90 → d > 10/3 ≈ 3.33。",
      "a₃₁ ≤ 100：(10−4d)+30d = 10+26d ≤ 100 → 26d ≤ 90 → d ≤ 45/13 ≈ 3.46。",
      "整数 d の条件：3.33 < d ≤ 3.46 には整数が存在しない（問題の設定再確認が必要）。"
    ],
    "common_mistakes": [
      "「第32項が100を超える」を「a₃₂ = 100」として等号で解く誤り。「超える」は > であり ≥ ではない。",
      "初項や公差が整数でない可能性を排除していない（問題文で整数条件を確認する）。"
    ],
    "tips": [
      "「最初に〜を超える」問題は a_{n−1} ≤ 値 < aₙ の連立不等式。",
      "整数条件がある場合は d の範囲を確定させてから全数チェックする。"
    ]
  },
  "as-025": {
    "lead": "k(k+1) = k²+k と分解して Σk² と Σk の公式を使うのが最も直接的な方法。",
    "steps": [
      "Σ[k=1,n] k(k+1) = Σ(k²+k) = Σk² + Σk。",
      "Σk² = n(n+1)(2n+1)/6、Σk = n(n+1)/2。",
      "合計 = n(n+1)(2n+1)/6 + n(n+1)/2 = n(n+1){(2n+1)/6 + 1/2} = n(n+1){(2n+1+3)/6} = n(n+1)(2n+4)/6。",
      "= n(n+1)×2(n+2)/6 = n(n+1)(n+2)/3。"
    ],
    "common_mistakes": [
      "Σk(k+1) = (Σk)×(Σ2^k) などとシグマを積に分離できると誤解するケース。シグマは和であり積ではない。",
      "通分の計算 (2n+1)/6 + 3/6 = (2n+4)/6 = (n+2)/3 の部分で算数ミスしやすい。"
    ],
    "tips": [
      "Σk² = n(n+1)(2n+1)/6、Σk = n(n+1)/2 は必須公式。",
      "k(k+1) = (1/3){(k+1)(k+2)k − k(k+1)(k−1)} を使うテレスコーピング法も有効（差の形で打ち消される）。"
    ]
  },
  "as-026": {
    "lead": "S₆ と S₃ = S₆ − (S₆−S₃) の2つの値から連立方程式を作る。",
    "steps": [
      "S₃ = S₆ − (S₆−S₃) = 48−21 = 27。",
      "S₃ = 3(2a+2d)/2 = 3(a+d) = 27 → a+d = 9 … ①。",
      "S₆ = 3(2a+5d) = 48 → 2a+5d = 16 … ②。",
      "② − 2×①：3d = 16−18 = −2 → d = −2/3。a = 9−(−2/3) = 9+2/3 = 29/3。"
    ],
    "common_mistakes": [
      "S₃ = 3(2a+2d)/2 の計算：S₃ = 3{2a+(3−1)d}/2 = 3(2a+2d)/2 = 3(a+d)。整理に注意。",
      "S₆−S₃ = 21 が「第4〜6項の和」と混同するケース。S₆−S₃ は a₄+a₅+a₆ の和。"
    ],
    "tips": [
      "Sₙ の2つの値から2式を立て、引き算で公差を求める。この流れは標準パターン。",
      "答えが分数になる場合でも正確に計算する。d = −2/3 は有理数で問題ない。"
    ]
  },
  "as-027": {
    "lead": "S₁₀ の式から 2a+9d=31 という一つの方程式を得て、a≥1, d≥1 の整数条件で解の個数を数える。",
    "steps": [
      "S₁₀ = 5(2a+9d) = 155 → 2a+9d = 31。",
      "a ≥ 1, d ≥ 1 の正の整数解を探す。",
      "d=1 → 2a = 22 → a = 11 ✓。d=2 → 2a = 13（奇数、整数解なし）。d=3 → 2a = 4 → a = 2 ✓。d=4 → 2a = 31−36 = −5 < 0（不適）。",
      "答え：2 通り（(a,d)=(11,1) と (2,3)）。"
    ],
    "common_mistakes": [
      "d が偶数のとき 2a = 31−9d が奇数になるので整数解なし。d の偶奇で判断できる。",
      "「9d < 31 → d ≤ 3」で候補を d=1,2,3 に絞れる（d ≥ 4 なら 9d ≥ 36 > 31 で a < 0）。"
    ],
    "tips": [
      "整数条件付きの和の問題は「範囲を絞ってから全数チェック」が確実。",
      "2a+9d=31 で 2a が偶数なので 9d も奇数。d が奇数 → 9d 奇数 → 2a 偶数（整合）。d が偶数 → 9d 偶数 → 31−偶数=奇数 → 2a が奇数（整数解なし）。"
    ]
  },
  "as-028": {
    "lead": "Sₙ = pn² + qn の係数と等差数列の和の公式を比較することで、公差と初項を p, q で直接表せる。",
    "steps": [
      "等差数列の和：Sₙ = n{2a+(n−1)d}/2 = (d/2)n² + (a−d/2)n。",
      "係数比較：d/2 = p → d = 2p。a−d/2 = q → a = q+d/2 = q+p。",
      "別解：a₁ = S₁ = p+q。aₙ = Sₙ−Sₙ₋₁ = p(2n−1)+q → d = 2p（n の係数）。"
    ],
    "common_mistakes": [
      "微分を使って dSₙ/dn = 2pn+q → 初項 2p+q と誤る。微分は離散の数列に直接使えない。",
      "公差 = Sₙ の最高次係数 p ではなく 2p。和の公式には d/2 という形で入っている。"
    ],
    "tips": [
      "Sₙ = pn²+qn 型の一般的な対応：初項 a = p+q、公差 d = 2p。",
      "これを覚えておくと Sₙ が与えられた問題を瞬時に解ける。"
    ]
  },
  "as-029": {
    "lead": "第m項=n、第n項=m という対称な条件から公差 d=−1 が直ちに導かれる。そこから第m+n項を求める。",
    "steps": [
      "aₘ = a+(m−1)d = n … ①、aₙ = a+(n−1)d = m … ②。",
      "① − ②：(m−n)d = n−m = −(m−n) → d = −1（m ≠ n）。",
      "① に代入：a+(m−1)(−1) = n → a = n+m−1。",
      "aₘ₊ₙ = a+(m+n−1)d = (m+n−1)+(m+n−1)(−1) = 0。"
    ],
    "common_mistakes": [
      "第m+n項を求めずに公差だけで終わる誤り。設問の指示（第m+n項を求める）まで計算を進める。",
      "a+(m+n−1)d に d=−1 を代入：(m+n−1) × (−1) = −(m+n−1)。a+{−(m+n−1)} = (m+n−1)−(m+n−1) = 0。"
    ],
    "tips": [
      "「第m項がnで第n項がm」という対称条件は公差 d=−1 を生む典型問題。",
      "第m+n項 = 0 は美しい結果。対称性から「m+n 番目の項が0」と覚えておく。"
    ]
  },
  "as-030": {
    "lead": "Sₙ/Tₙ の比から aₙ/bₙ を求めるには「n に 2n−1 を代入する」という技法を使う。",
    "steps": [
      "等差数列の和：Sₙ = n×(a₁+aₙ)/2 → Sₙ/n = (a₁+aₙ)/2 = 中央値（n 項の平均）。",
      "aₖ = Sₙ/n で n を 2k−1 に置いた値に等しい（k 番目の項は (2k−1) 項の和の平均）。",
      "n=2×7−1=13 を Sₙ/Tₙ に代入：a₇/b₇ = S₁₃/T₁₃ = (3×13+1)/(2×13+5) = 40/31。"
    ],
    "common_mistakes": [
      "n=7 を直接代入して S₇/T₇ = 22/19 を求める誤り。Sₙ/Tₙ の n に 7 を代入しても a₇/b₇ にはならない。",
      "「Sₙ/Tₙ の n に 2n−1 を代入」の意味：数列の第 n 項は「その項を中央にした奇数項の和の比」と等しい。"
    ],
    "tips": [
      "Sₙ/Tₙ = f(n) のとき aₙ/bₙ = f(2n−1)。これは頻出の公式テクニック。",
      "第7項を求めるなら n=2×7−1=13 を代入。覚えておくと試験で素早く解ける。"
    ]
  }
}