{
  "pol-001": {
    "lead": "log₂8 = 3 です。「2を何乗すると8になるか」を考えると、2³=8 なので答えは3です。",
    "steps": [
      "logₐb=x ↔ aˣ=b の定義を確認する",
      "log₂8=x → 2ˣ=8 となる x を求める",
      "2³=8 なので x=3"
    ],
    "common_mistakes": [
      "log₂8=4 と誤解する（2⁴=16 との混同）",
      "log₂8=8 と底と真数を混同する"
    ],
    "tips": [
      "対数は「何乗するか」を表す。log₂8=3 は「2を3乗すると8」という意味"
    ]
  },
  "pol-002": {
    "lead": "log₁₀100 = 2 です。10²=100 なので答えは2です。",
    "steps": [
      "log₁₀100=x → 10ˣ=100 となる x を求める",
      "10²=100 なので x=2"
    ],
    "common_mistakes": [
      "log₁₀100=100 と真数をそのまま答えてしまう",
      "log₁₀100=10 と底をそのまま答えてしまう"
    ],
    "tips": [
      "10のべき乗は暗記しておくと便利：10¹=10, 10²=100, 10³=1000"
    ]
  },
  "pol-003": {
    "lead": "logₐ1 = 0 です。a⁰=1 なので、どんな底でも1の対数は0になります。",
    "steps": [
      "logₐ1=x → aˣ=1 となる x を求める",
      "a⁰=1 なので x=0"
    ],
    "common_mistakes": [
      "logₐ1=1 と混同する（logₐa=1 との混同）",
      "logₐ1=a と底をそのまま答える"
    ],
    "tips": [
      "logₐ1=0 と logₐa=1 はセットで覚えよう"
    ]
  },
  "pol-004": {
    "lead": "logₐa = 1 です。a¹=a なので、底と真数が同じとき対数は1です。",
    "steps": [
      "logₐa=x → aˣ=a となる x を求める",
      "a¹=a なので x=1"
    ],
    "common_mistakes": [
      "logₐa=0 と混同する（logₐ1=0 との混同）",
      "logₐa=a と底の値をそのまま答える"
    ],
    "tips": [
      "logₐ1=0、logₐa=1 の2つは対数の基本公式として必ず覚えること"
    ]
  },
  "pol-005": {
    "lead": "log₂(4×8) は積の対数の法則で log₂4+log₂8=2+3=5 です。",
    "steps": [
      "logₐ(MN)=logₐM+logₐN の公式を適用",
      "log₂4=2（2²=4）、log₂8=3（2³=8）",
      "2+3=5"
    ],
    "common_mistakes": [
      "log₂4×log₂8=2×3=6 と対数の掛け算にしてしまう",
      "log₂4+log₂8=2+8=10 と log₂8=8 と誤計算する"
    ],
    "tips": [
      "「積の対数 = 対数の和」log(MN)=logM+logN は最頻出公式の一つ"
    ]
  },
  "pol-006": {
    "lead": "log₃9−log₃3 は商の対数の法則で log₃(9/3)=log₃3=1 です。",
    "steps": [
      "logₐM−logₐN=logₐ(M/N) の公式を適用",
      "log₃(9/3)=log₃3",
      "3¹=3 なので log₃3=1"
    ],
    "common_mistakes": [
      "log₃(9−3)=log₃6 と真数を引いてしまう",
      "log₃9÷log₃3=2÷1=2 と対数を割ってしまう"
    ],
    "tips": [
      "「差の対数 = 対数の商」log(M/N)=logM−logN"
    ]
  },
  "pol-007": {
    "lead": "log₂8³ はべき乗の対数の法則で 3log₂8=3×3=9 です。指数を前に出せるのが重要な性質です。",
    "steps": [
      "logₐMⁿ=n×logₐM の公式を適用",
      "log₂8³=3×log₂8",
      "log₂8=3（2³=8）なので 3×3=9"
    ],
    "common_mistakes": [
      "(log₂8)³=3³=27 と対数全体を3乗してしまう",
      "log₂(8+3)=log₂11 と指数を加算してしまう"
    ],
    "tips": [
      "logₐMⁿ=n logₐM は指数を前に出す公式。計算を簡単にする強力なツール"
    ]
  },
  "pol-008": {
    "lead": "log(M×N)=logM+logN が成立するには M>0 かつ N>0 が必要です。対数は正の数にしか定義されません。",
    "steps": [
      "対数 logₐx は x>0 のときのみ定義される",
      "よって M と N の両方が正の数である必要がある"
    ],
    "common_mistakes": [
      "M>0 だけでよいと思う（N>0 も必須）",
      "M≠0 かつ N≠0 で十分と思う（負の数は不可）"
    ],
    "tips": [
      "対数の真数条件「真数>0」は方程式・不等式を解く際に毎回確認が必要"
    ]
  },
  "pol-009": {
    "lead": "log₂(1/8) = −3 です。1/8=2⁻³ なので log₂(2⁻³)=−3 となります。",
    "steps": [
      "1/8=2⁻³ と変換する",
      "log₂(2⁻³)=−3"
    ],
    "common_mistakes": [
      "log₂(1/8)=−8 と真数の逆数をそのまま使う",
      "log₂(1/8)=3 と負号を落とす"
    ],
    "tips": [
      "1/aⁿ=a⁻ⁿ なので log₂(1/8)=log₂(2⁻³)=−3。負の対数の値は頻出"
    ]
  },
  "pol-010": {
    "lead": "log₂4+log₂2 は積の対数の法則で log₂(4×2)=log₂8=3 です。",
    "steps": [
      "logₐM+logₐN=logₐ(MN) の公式を使う",
      "log₂4+log₂2=log₂(4×2)=log₂8",
      "2³=8 なので log₂8=3"
    ],
    "common_mistakes": [
      "log₂(4+2)=log₂6 と真数を足してしまう（選択肢A）",
      "log₂4=2 だけを答え、log₂2=1 の項を忘れてしまう（選択肢B）",
      "log₂4を4と誤解して log₂4×log₂2=4×1=4 と掛けてしまう（選択肢C）"
    ],
    "tips": [
      "対数の和は真数の積：logM+logN=log(MN)。真数どうしを足すのは間違い"
    ]
  },
  "pol-011": {
    "lead": "底の変換公式 logₐb=logb/loga です（常用対数で底を統一できます）。",
    "steps": [
      "logₐb = logcb/logca（任意の底cを使って変換）",
      "常用対数を使う場合：logₐb = log₁₀b/log₁₀a = logb/loga"
    ],
    "common_mistakes": [
      "logₐb=loga/logb と分子分母を逆にしてしまう",
      "logₐb=logb×loga と掛け算にしてしまう"
    ],
    "tips": [
      "底の変換公式：分子が「真数の対数」、分母が「底の対数」"
    ]
  },
  "pol-012": {
    "lead": "log₂3×log₃8 は底の変換で log₃8=log₂8/log₂3 に変換し、約分すると log₂8=3 になります。",
    "steps": [
      "底の変換：log₃8=log₂8/log₂3",
      "log₂3 × (log₂8/log₂3) = log₂8",
      "log₂8=3（2³=8）"
    ],
    "common_mistakes": [
      "log₂3×log₃8=log₅11 と底や真数を足してしまう",
      "log₂3×log₃8=6 と単純な掛け算をしてしまう",
      "log₃8=3 と誤解して log₂3 × 3=3log₂3 と計算してしまう（3³=27≠8 なので log₃8≠3）"
    ],
    "tips": [
      "連鎖する対数（logₐb×logbc=logₐc）は底の変換で約分できる頻出パターン"
    ]
  },
  "pol-013": {
    "lead": "log₂50=log₂(2×25)=1+log₂25=1+2log₂5=1+2a です。50=2×5² と因数分解するのがポイントです。",
    "steps": [
      "50=2×25=2×5² と分解",
      "log₂50=log₂2+log₂5²=1+2log₂5",
      "log₂5=a を代入して 1+2a"
    ],
    "common_mistakes": [
      "log₂50=a+5 と対数に50を加えてしまう",
      "log₂50=2a と log₂2=1 の部分を忘れる"
    ],
    "tips": [
      "真数を素因数分解して底の2が含まれる部分を分離するのが定石"
    ]
  },
  "pol-014": {
    "lead": "logₐb²=2logₐb が成立するには b>0 が必要です。b<0 では logₐb が定義されません。",
    "steps": [
      "logₐb²=2logₐb は logₐMⁿ=n logₐM の公式",
      "この公式が使えるのは真数 b が正の数のとき（b>0）",
      "b<0 では logₐb 自体が定義されない"
    ],
    "common_mistakes": [
      "b は任意の実数でよいと思う（b<0 は対数の定義域外）",
      "b>1 が必要と思う（b>0 であれば十分）"
    ],
    "tips": [
      "「真数>0」の条件は常に意識すること"
    ]
  },
  "pol-015": {
    "lead": "log₁₀5=log₁₀(10/2)=1−log₁₀2=1−0.301=0.699 です。5=10÷2 と変換するのがポイントです。",
    "steps": [
      "5=10/2 と変換する",
      "log₁₀5=log₁₀(10/2)=log₁₀10−log₁₀2",
      "=1−0.301=0.699"
    ],
    "common_mistakes": [
      "log₁₀5=0.301 と log₁₀2 と同じ値にしてしまう（選択肢D）",
      "log₁₀5=0.7 と概算にしてしまう（0.699 が正確な値）（選択肢C）",
      "log₁₀(2+3)=log₁₀2+log₁₀3=0.778 と誤って対数の加法定理を適用する（log(M+N)≠logM+logN）（選択肢B）"
    ],
    "tips": [
      "log₁₀5=1−log₁₀2 は頻出。log₁₀2≒0.301 と合わせて必ず覚えよう"
    ]
  },
  "pol-016": {
    "lead": "2^(log₂3) = 3 です。a^(logₐN)=N という公式により、答えは真数の3です。",
    "steps": [
      "a^(logₐN)=N の公式を確認する",
      "2^(log₂3) → 底が 2 で指数も log₂（底 2）",
      "N=3 → 答えは 3"
    ],
    "common_mistakes": [
      "9 と誤解する（log₂3 を誤計算）",
      "2×3=6 と底と真数を掛けてしまう"
    ],
    "tips": [
      "a^(logₐN)=N は指数関数と対数関数が互いに逆関数であることの表れ"
    ]
  },
  "pol-017": {
    "lead": "log₂12=log₂(4×3)=log₂4+log₂3=2+a です。12=4×3=2²×3 と分解します。",
    "steps": [
      "12=4×3=2²×3 と分解",
      "log₂12=log₂4+log₂3=2+log₂3",
      "log₂3=a を代入して 2+a"
    ],
    "common_mistakes": [
      "log₂12=2a と log₂4=2 の部分を忘れる",
      "log₂12=3+a と log₂4=3 と誤計算する"
    ],
    "tips": [
      "真数を 2のべき乗 × 既知の値 に分解するのが文字置換問題の定石"
    ]
  },
  "pol-018": {
    "lead": "log₃(2x+1)=2 → 2x+1=3²=9 → x=4 です。logₐM=n ↔ M=aⁿ に変換します。",
    "steps": [
      "logₐM=n ↔ M=aⁿ を利用",
      "2x+1=3²=9",
      "2x=8 → x=4",
      "真数確認：2×4+1=9>0 ✓"
    ],
    "common_mistakes": [
      "2x=3²=9 → x=9/2 と、+1 を無視して 2x=9 としてしまう",
      "2x+1=3×2=6 と底と指数を掛けてしまう",
      "2x+1=3+2=5 と誤解する"
    ],
    "tips": [
      "対数方程式は「logₐM=k → M=aᵏ」に変換してから解く"
    ]
  },
  "pol-019": {
    "lead": "log₂x>3 を解くと x>2³=8 です。底 2>1 なので不等号の向きはそのまま。",
    "steps": [
      "log₂x>3 → x>2³=8（底 2>1 なので不等号の向きそのまま）",
      "真数条件 x>0 は x>8 で自動的に満たされる"
    ],
    "common_mistakes": [
      "x<8 と不等号を逆にしてしまう",
      "x>3/log₂ と対数を線形に扱ってしまう"
    ],
    "tips": [
      "対数不等式：底>1なら不等号そのまま、0<底<1なら逆転"
    ]
  },
  "pol-020": {
    "lead": "logₐb×logbₐ=1 です。底の変換で logbₐ=1/logₐb と変換すると、かけると1になります。",
    "steps": [
      "底の変換公式：logbₐ=1/logₐb",
      "logₐb × (1/logₐb)=1"
    ],
    "common_mistakes": [
      "logₐb×logbₐ=0 と誤解する",
      "logₐb×logbₐ=2 と誤解する"
    ],
    "tips": [
      "logₐb と logbₐ は互いに逆数の関係：logₐb×logbₐ=1"
    ]
  },
  "pol-021": {
    "lead": "log₁₀(6¹⁰)=10log₁₀6=10×0.778=7.78 なので、6¹⁰ は8桁です。",
    "steps": [
      "log₁₀6=log₁₀(2×3)=0.301+0.477=0.778",
      "log₁₀(6¹⁰)=10×0.778=7.78",
      "7≤log₁₀N<8 のとき N は 8桁"
    ],
    "common_mistakes": [
      "7.78 → 7桁と誤解する（整数部分+1が桁数）",
      "7.78 → 10桁と誤解する"
    ],
    "tips": [
      "n桁の整数 N ↔ n−1≤log₁₀N<n。log₁₀N の整数部分+1が桁数"
    ]
  },
  "pol-022": {
    "lead": "log₂x(x−1)=1 → x(x−1)=2 → (x−2)(x+1)=0。真数条件 x>1 より x=2 です。",
    "steps": [
      "積の対数：log₂x+log₂(x−1)=log₂x(x−1)=1",
      "x(x−1)=2¹=2 → x²−x−2=0 → (x−2)(x+1)=0",
      "真数条件：x>0 かつ x−1>0 → x>1",
      "x=2（x=−1 は棄却）"
    ],
    "common_mistakes": [
      "x=−1 を採用する（真数条件で棄却）",
      "x=1 と誤解する"
    ],
    "tips": [
      "対数方程式では必ず真数条件を確認し、不適な解を棄却すること"
    ]
  },
  "pol-023": {
    "lead": "x(x+6)=27 → (x+9)(x−3)=0。真数条件 x>0 より x=3 です。",
    "steps": [
      "log₃x+log₃(x+6)=log₃x(x+6)=3",
      "x(x+6)=3³=27 → x²+6x−27=0",
      "(x+9)(x−3)=0 → x=−9 または x=3",
      "真数条件 x>0 → x=3（x=−9 は棄却）"
    ],
    "common_mistakes": [
      "x=−9 を採用する（真数条件で棄却される）",
      "x=3 と x=−9 の両方を答える"
    ],
    "tips": [
      "2次方程式の解が出たら真数条件で必ず絞り込む。負の解は多くの場合棄却される"
    ]
  },
  "pol-024": {
    "lead": "底 2>1 なので x≤3−x → x≤3/2。真数条件 x>0 かつ x<3 より 0<x≤3/2 です。",
    "steps": [
      "底 2>1 → 単調増加なので x≤3−x",
      "2x≤3 → x≤3/2",
      "真数条件：x>0 かつ 3−x>0(x<3) → 0<x≤3/2"
    ],
    "common_mistakes": [
      "真数条件を確認せず x≤3/2 とだけ答える",
      "x<3/2 と等号を外してしまう"
    ],
    "tips": [
      "対数不等式では①底の大小確認→不等号方向決定、②真数条件確認の2ステップ"
    ]
  },
  "pol-025": {
    "lead": "底の変換で log₁₄12=log₂12/log₂14=(2+a)/(1+b) です。",
    "steps": [
      "底の変換：log₁₄12=log₂12/log₂14",
      "log₂12=log₂(4×3)=2+a",
      "log₂14=log₂(2×7)=1+b",
      "(2+a)/(1+b)"
    ],
    "common_mistakes": [
      "(a+b)/(2+a) と分子・分母を逆に設定する",
      "(1+a)/(1+b) と log₂12 の計算を誤る"
    ],
    "tips": [
      "底の変換後に各対数を素因数分解して既知の値に置き換えるのが定石"
    ]
  },
  "pol-026": {
    "lead": "(log₂3)²+log₂3×log₂(1/3)=0 です。a=log₂3 とすると log₂(1/3)=−a なので a²−a²=0。",
    "steps": [
      "a=log₂3 とおく",
      "log₂(1/3)=log₂3⁻¹=−log₂3=−a",
      "a²+a×(−a)=a²−a²=0"
    ],
    "common_mistakes": [
      "log₂(1/3)=log₂3 と誤解する",
      "(log₂3)²=1 などと計算する"
    ],
    "tips": [
      "log₂(1/3)=−log₂3 という変換が鍵"
    ]
  },
  "pol-027": {
    "lead": "log₁₀(2⁴⁰)=40×0.301=12.04 なので、2⁴⁰ は13桁です。",
    "steps": [
      "log₁₀(2⁴⁰)=40×log₁₀2=40×0.301=12.04",
      "12≤log₁₀N<13 → N は 13桁"
    ],
    "common_mistakes": [
      "12.04 → 12桁と誤解する（整数部分12、桁数は12+1=13）",
      "12.04 → 14桁と誤解する"
    ],
    "tips": [
      "log₁₀N の整数部分を n とすると、N は n+1 桁。12.04 → 整数部分12 → 13桁"
    ]
  },
  "pol-028": {
    "lead": "logbₐ=1/logₐb=1/2 です。logₐb と logbₐ は互いに逆数の関係です。",
    "steps": [
      "底の変換：logbₐ=1/logₐb",
      "logₐb=2 なので logbₐ=1/2"
    ],
    "common_mistakes": [
      "logbₐ=2 と logₐb と同じ値と誤解する",
      "logbₐ=−2 と符号を変えてしまう"
    ],
    "tips": [
      "logₐb×logbₐ=1 → logbₐ=1/logₐb。この逆数関係は頻出"
    ]
  },
  "pol-029": {
    "lead": "log₄8=log₂8/log₂4=3/2 です。底の変換で底を2に統一します。",
    "steps": [
      "底の変換：log₄8=log₂8/log₂4",
      "log₂8=3（2³=8）、log₂4=2（2²=4）",
      "3/2"
    ],
    "common_mistakes": [
      "log₄8=3 と誤解する（4³=64≠8）",
      "log₄8=2 と誤解する（4²=16≠8）"
    ],
    "tips": [
      "底の変換は「共通の底（2や10など）を使って変換する」のが定石"
    ]
  },
  "pol-030": {
    "lead": "t=log₂x と置くと t²−t−2=0 → (t−2)(t+1)=0 → x=4 または x=1/2 です。",
    "steps": [
      "t=log₂x と置くと (log₂x)²=t²",
      "t²−t−2=0 を因数分解：(t−2)(t+1)=0",
      "t=2 → log₂x=2 → x=4",
      "t=−1 → log₂x=−1 → x=1/2",
      "真数条件 x>0 はどちらも満たす"
    ],
    "common_mistakes": [
      "x=2 のみと誤解する（t=log₂x=1 → x=2 という誤計算）",
      "x=4 のみと答える（t=−1 の解 x=1/2 を見落とす）"
    ],
    "tips": [
      "t=log₂x の置換で2次方程式になるパターンは頻出。2解とも確認すること"
    ]
  }
}